revisions/__init__.py
revisions/core.py
revisions-0.2.0.dist-info/DESCRIPTION.rst
revisions-0.2.0.dist-info/METADATA
revisions-0.2.0.dist-info/metadata.json
revisions-0.2.0.dist-info/RECORD
revisions-0.2.0.dist-info/top_level.txt
revisions-0.2.0.dist-info/WHEEL
