Metadata-Version: 2.0
Name: revisions
Version: 0.2.0
Summary: Mock Python Requests with versioned cache control.
Home-page: https://github.com/PrashntS/revisions
Author: Prashant Sinha
Author-email: prashant@ducic.ac.in
License: MIT
Platform: UNKNOWN
Classifier: Development Status :: 3 - Alpha
Classifier: Intended Audience :: Developers
Classifier: License :: OSI Approved :: MIT License
Classifier: Programming Language :: Python
Classifier: Programming Language :: Python :: 2
Classifier: Programming Language :: Python :: 3
Classifier: Topic :: Software Development :: Testing
